desktop_application/__init__.py
desktop_application/__main__.py
obff/__init__.py
obff/__vars__.py
obff/obff.py
obff/obff_class.py
obff/utils.py
obff/desktop_application/__init__.py
obff/desktop_application/__main__.py
obff-1.0.1.dist-info/LICENSE
obff-1.0.1.dist-info/METADATA
obff-1.0.1.dist-info/WHEEL
obff-1.0.1.dist-info/entry_points.txt
obff-1.0.1.dist-info/top_level.txt
obff-1.0.1.dist-info/RECORD
