Metadata-Version: 2.1
Name: obff
Version: 1.0.1
Summary: Parser "for Open Book File Format"
Home-page: https://github.com/obff-development/obff-python/
Author: obff-development
Author-email: mc25.studio@gmail.com
License: UNKNOWN
Project-URL: Issue tracker, https://github.com/obff-development/obff-python/issues
Platform: UNKNOWN
Classifier: Development Status :: 1 - Planning
Classifier: Programming Language :: Python :: 3.5
Classifier: Programming Language :: Python :: 3.9
Classifier: License :: OSI Approved :: GNU General Public License v3 (GPLv3)
Classifier: Operating System :: OS Independent
Classifier: Topic :: Adaptive Technologies
Requires-Python: >=3.5
License-File: LICENSE
